[
  {
    "id": 1,
    "projectTitle": "AI Document Summarizer",
    "slug": "suitefiles-ai-summary",
    "projectImage": "public/images/portfolio/suitefiles-ai-summary-cover.png",
    "company": "SuiteFiles"
  },
  {
    "id": 2,
    "projectTitle": "Design System",
    "slug": "suitefiles-design-system",
    "projectImage": "/images/portfolio/suitefiles-design-system-cover.png",
    "company": "SuiteFiles"
  },
  {
    "id": 3,
    "projectTitle": "Design System",
    "slug": "moe-design-system",
    "projectImage": "/images/portfolio/moe-design-system-cover.png",
    "company": "Ministry of Education"
  },
  {
    "id": 4,
    "projectTitle": "Templates",
    "slug": "ow-templates",
    "projectImage": "/images/portfolio/optimal-homepage-cover.png",
    "company": "Optimal Workshop"
  }
]
